vibhakar/__init__.py
vibhakar-1.0.3.dist-info/LICENSE
vibhakar-1.0.3.dist-info/METADATA
vibhakar-1.0.3.dist-info/WHEEL
vibhakar-1.0.3.dist-info/entry_points.txt
vibhakar-1.0.3.dist-info/RECORD
